sidemantic/__init__.py
sidemantic/charts.py
sidemantic/cli.py
sidemantic/config.py
sidemantic/loaders.py
sidemantic/mcp_server.py
sidemantic/schema.py
sidemantic/validation.py
sidemantic/adapters/base.py
sidemantic/adapters/bsl.py
sidemantic/adapters/bsl_expr.py
sidemantic/adapters/cube.py
sidemantic/adapters/hex.py
sidemantic/adapters/lookml.py
sidemantic/adapters/malloy.py
sidemantic/adapters/metricflow.py
sidemantic/adapters/omni.py
sidemantic/adapters/rill.py
sidemantic/adapters/sidemantic.py
sidemantic/adapters/snowflake.py
sidemantic/adapters/superset.py
sidemantic/adapters/malloy_grammar/MalloyLexer.g4
sidemantic/adapters/malloy_grammar/MalloyLexer.interp
sidemantic/adapters/malloy_grammar/MalloyLexer.py
sidemantic/adapters/malloy_grammar/MalloyLexer.tokens
sidemantic/adapters/malloy_grammar/MalloyParser.g4
sidemantic/adapters/malloy_grammar/MalloyParser.interp
sidemantic/adapters/malloy_grammar/MalloyParser.py
sidemantic/adapters/malloy_grammar/MalloyParser.tokens
sidemantic/adapters/malloy_grammar/MalloyParserListener.py
sidemantic/adapters/malloy_grammar/MalloyParserVisitor.py
sidemantic/adapters/malloy_grammar/__init__.py
sidemantic/core/catalog.py
sidemantic/core/dependency_analyzer.py
sidemantic/core/dialect.py
sidemantic/core/dimension.py
sidemantic/core/inheritance.py
sidemantic/core/metric.py
sidemantic/core/migrator.py
sidemantic/core/model.py
sidemantic/core/parameter.py
sidemantic/core/pre_aggregation.py
sidemantic/core/preagg_matcher.py
sidemantic/core/preagg_recommender.py
sidemantic/core/registry.py
sidemantic/core/relationship.py
sidemantic/core/relative_date.py
sidemantic/core/segment.py
sidemantic/core/semantic_graph.py
sidemantic/core/semantic_layer.py
sidemantic/core/sql_definitions.py
sidemantic/core/symmetric_aggregate.py
sidemantic/core/table_calculation.py
sidemantic/core/template.py
sidemantic/core/time_intelligence.py
sidemantic/db/__init__.py
sidemantic/db/adbc.py
sidemantic/db/base.py
sidemantic/db/bigquery.py
sidemantic-0.5.11.dist-info/METADATA
sidemantic-0.5.11.dist-info/WHEEL
sidemantic-0.5.11.dist-info/entry_points.txt
sidemantic-0.5.11.dist-info/licenses/LICENSE
sidemantic-0.5.11.dist-info/RECORD
