Metadata-Version: 2.4
Name: sidemantic
Version: 0.5.11
Summary: Universal semantic layer - import from Cube, dbt, LookML, Hex, and more
License:                     GNU AFFERO GENERAL PUBLIC LICENSE
License-File: LICENSE
Requires-Python: >=3.11
Requires-Dist: duckdb>=1.0.0
Requires-Dist: inflect<7.2.0,>=7.0.0
Requires-Dist: jinja2>=3.1.0
Requires-Dist: lkml>=1.3.7
Requires-Dist: pydantic>=2.0.0
Requires-Dist: pyyaml>=6.0
Requires-Dist: sqlglot==27.12.0
Requires-Dist: typer>=0.9.0
Provides-Extra: adbc
Requires-Dist: adbc-driver-manager>=1.0.0; extra == 'adbc'
Requires-Dist: pyarrow>=14.0.0; extra == 'adbc'
Provides-Extra: all-databases
Requires-Dist: adbc-driver-manager>=1.0.0; extra == 'all-databases'
Requires-Dist: clickhouse-connect>=0.6.0; extra == 'all-databases'
Requires-Dist: databricks-sql-connector>=2.0.0; extra == 'all-databases'
Requires-Dist: google-cloud-bigquery>=3.0.0; extra == 'all-databases'
Requires-Dist: psycopg[binary]>=3.0.0; extra == 'all-databases'
Requires-Dist: pure-sasl>=0.6.2; extra == 'all-databases'
Requires-Dist: pyarrow>=14.0.0; extra == 'all-databases'
Requires-Dist: pyhive>=0.7.0; extra == 'all-databases'
Requires-Dist: snowflake-connector-python>=3.0.0; extra == 'all-databases'
Requires-Dist: thrift-sasl>=0.4.3; extra == 'all-databases'
Requires-Dist: thrift>=0.16.0; extra == 'all-databases'
Provides-Extra: bigquery
Requires-Dist: google-cloud-bigquery>=3.0.0; extra == 'bigquery'
Requires-Dist: pyarrow>=14.0.0; extra == 'bigquery'
Provides-Extra: charts
Requires-Dist: altair>=5.0.0; extra == 'charts'
Requires-Dist: vl-convert-python>=1.0.0; extra == 'charts'
Provides-Extra: clickhouse
Requires-Dist: clickhouse-connect>=0.6.0; extra == 'clickhouse'
Requires-Dist: pyarrow>=14.0.0; extra == 'clickhouse'
Provides-Extra: databricks
Requires-Dist: databricks-sql-connector>=2.0.0; extra == 'databricks'
Requires-Dist: pyarrow>=14.0.0; extra == 'databricks'
Provides-Extra: dev
Requires-Dist: fakesnow>=0.9.0; extra == 'dev'
Requires-Dist: numpy<3,>=1.26; extra == 'dev'
Requires-Dist: pandas<3,>=2.2; extra == 'dev'
Requires-Dist: pytest-cov>=5.0.0; extra == 'dev'
Requires-Dist: pytest>=8.0.0; extra == 'dev'
Requires-Dist: ruff>=0.6.0; extra == 'dev'
Provides-Extra: full
Requires-Dist: altair>=5.0.0; extra == 'full'
Requires-Dist: antlr4-python3-runtime>=4.13.2; extra == 'full'
Requires-Dist: anywidget>=0.9.0; extra == 'full'
Requires-Dist: lsprotocol>=2025.0.0; extra == 'full'
Requires-Dist: mcp[cli]>=1.16.0; extra == 'full'
Requires-Dist: plotext>=5.3.2; extra == 'full'
Requires-Dist: pyarrow>=14.0.0; extra == 'full'
Requires-Dist: pygls>=2.0.0; extra == 'full'
Requires-Dist: textual-plotext>=1.0.1; extra == 'full'
Requires-Dist: textual[syntax]>=1.0.0; extra == 'full'
Requires-Dist: vl-convert-python>=1.0.0; extra == 'full'
Provides-Extra: lsp
Requires-Dist: lsprotocol>=2025.0.0; extra == 'lsp'
Requires-Dist: pygls>=2.0.0; extra == 'lsp'
Provides-Extra: malloy
Requires-Dist: antlr4-python3-runtime>=4.13.2; extra == 'malloy'
Provides-Extra: mcp
Requires-Dist: mcp[cli]>=1.16.0; extra == 'mcp'
Provides-Extra: postgres
Requires-Dist: psycopg[binary]>=3.0.0; extra == 'postgres'
Requires-Dist: pyarrow>=14.0.0; extra == 'postgres'
Provides-Extra: serve
Requires-Dist: pyarrow>=14.0.0; extra == 'serve'
Requires-Dist: riffq>=0.1.0; extra == 'serve'
Provides-Extra: snowflake
Requires-Dist: pyarrow>=14.0.0; extra == 'snowflake'
Requires-Dist: snowflake-connector-python>=3.0.0; extra == 'snowflake'
Provides-Extra: spark
Requires-Dist: pure-sasl>=0.6.2; extra == 'spark'
Requires-Dist: pyarrow>=14.0.0; extra == 'spark'
Requires-Dist: pyhive>=0.7.0; extra == 'spark'
Requires-Dist: thrift-sasl>=0.4.3; extra == 'spark'
Requires-Dist: thrift>=0.16.0; extra == 'spark'
Provides-Extra: widget
Requires-Dist: anywidget>=0.9.0; extra == 'widget'
Requires-Dist: pyarrow>=14.0.0; extra == 'widget'
Provides-Extra: workbench
Requires-Dist: plotext>=5.3.2; extra == 'workbench'
Requires-Dist: textual-plotext>=1.0.1; extra == 'workbench'
Requires-Dist: textual[syntax]>=1.0.0; extra == 'workbench'
